jiangsu_jqyeviuijksd/__init__.py
jiangsu_jqyeviuijksd/answer_question.py
jiangsu_jqyeviuijksd/common.py
jiangsu_jqyeviuijksd/console.py
jiangsu_jqyeviuijksd/get_proxy.py
jiangsu_jqyeviuijksd/get_question.py
jiangsu_jqyeviuijksd/get_session.py
jiangsu_jqyeviuijksd/questions.json
jiangsu_jqyeviuijksd/school_prefix.py
jiangsu_jqyeviuijksd-0.1.3.dist-info/entry_points.txt
jiangsu_jqyeviuijksd-0.1.3.dist-info/LICENSE
jiangsu_jqyeviuijksd-0.1.3.dist-info/WHEEL
jiangsu_jqyeviuijksd-0.1.3.dist-info/METADATA
jiangsu_jqyeviuijksd-0.1.3.dist-info/RECORD
