Metadata-Version: 2.1
Name: jiangsu-jqyeviuijksd
Version: 0.1.3
Summary: 可用于江苏就业知识竞赛的自动答题, 主要用于 Python 和 HTTP 的入门
Home-page: https://github.com/myuanz/jiangsu-jqyeviuijksd
License: GPL-3.0-or-later
Keywords: 就业知识竞赛,就业知识,江苏,自动答题,Python 新手入门
Author: provefar
Author-email: provefars@gmail.com
Requires-Python: >=3.7
Classifier: License :: OSI Approved :: GNU General Public License v3 or later (GPLv3+)
Classifier: Programming Language :: Python :: 3
Classifier: Programming Language :: Python :: 3.7
Classifier: Programming Language :: Python :: 3.8
Requires-Dist: faker (>=4.1.3,<5.0.0)
Requires-Dist: lxml (>=4.5.2,<5.0.0)
Requires-Dist: muggle-ocr (>=1.0.3,<2.0.0)
Requires-Dist: pathlib2 (>=2.3.5,<3.0.0)
Requires-Dist: requests (>=2.24.0)
Project-URL: Repository, https://github.com/myuanz/jiangsu-jqyeviuijksd
